{
  "patient": {
    "pat_id": "PAT0100540",
    "med_rec_num": "MRN0200540",
    "full_name": "Richard Gonzalez",
    "birth_date": "1948-08-07",
    "age": 78,
    "sex": "M",
    "city": "Pittsburgh",
    "zip_code": "15222",
    "primary_care_provider": "Dr. Aisha Anderson",
    "active_chronic_count": 2,
    "encounter_count": 9,
    "total_charges": 2615,
    "latitude": 40.44814,
    "longitude": -79.99124,
    "last_encounter_date": "2026-03-25",
    "race": "Hispanic/Latino",
    "ethnicity": "Not Hispanic or Latino",
    "mailing_address": "1694 Walnut Ave",
    "state": "PA",
    "phone": "(412) 892-6741",
    "primary_care_department": "Urgent Care \u2014 Mt Lebanon"
  },
  "encounters": {
    "pat_id": "PAT0100540",
    "encounters": [
      {
        "pat_enc_csn_id": "0000540-000",
        "contact_date": "2026-03-25",
        "encounter_type": "Office Visit",
        "department_name": "Emergency Department \u2014 Main",
        "provider_name": "Dr. Mark Gonzalez",
        "chief_complaint": "Unspecified abdominal pain",
        "diagnosis_count": 3,
        "total_charges": 286
      },
      {
        "pat_enc_csn_id": "0000540-001",
        "contact_date": "2026-01-03",
        "encounter_type": "Telehealth",
        "department_name": "Internal Medicine \u2014 Squirrel Hill",
        "provider_name": "Dr. Aisha Anderson",
        "chief_complaint": null,
        "diagnosis_count": 2,
        "total_charges": 187
      },
      {
        "pat_enc_csn_id": "0000540-002",
        "contact_date": "2025-12-06",
        "encounter_type": "Office Visit",
        "department_name": "Pulmonology",
        "provider_name": "Dr. Aisha Anderson",
        "chief_complaint": "Contusion of head",
        "diagnosis_count": 3,
        "total_charges": 416
      },
      {
        "pat_enc_csn_id": "0000540-003",
        "contact_date": "2025-11-26",
        "encounter_type": "Telehealth",
        "department_name": "Orthopedics",
        "provider_name": "Dr. Sophia Gonzalez",
        "chief_complaint": "Chest pain, unspecified",
        "diagnosis_count": 3,
        "total_charges": 212
      },
      {
        "pat_enc_csn_id": "0000540-004",
        "contact_date": "2025-11-22",
        "encounter_type": "Office Visit",
        "department_name": "Psychiatry & Behavioral Health",
        "provider_name": "Dr. Aisha Anderson",
        "chief_complaint": "Headache",
        "diagnosis_count": 3,
        "total_charges": 380
      },
      {
        "pat_enc_csn_id": "0000540-005",
        "contact_date": "2025-08-22",
        "encounter_type": "Office Visit",
        "department_name": "Psychiatry & Behavioral Health",
        "provider_name": "Dr. Daniel Jackson",
        "chief_complaint": null,
        "diagnosis_count": 2,
        "total_charges": 228
      },
      {
        "pat_enc_csn_id": "0000540-006",
        "contact_date": "2025-04-26",
        "encounter_type": "Office Visit",
        "department_name": "Family Medicine \u2014 North Hills",
        "provider_name": "Dr. Mark Thomas",
        "chief_complaint": "Acute upper respiratory infection",
        "diagnosis_count": 3,
        "total_charges": 192
      },
      {
        "pat_enc_csn_id": "0000540-007",
        "contact_date": "2025-01-10",
        "encounter_type": "Office Visit",
        "department_name": "Pulmonology",
        "provider_name": "Dr. Ashley Garcia",
        "chief_complaint": null,
        "diagnosis_count": 2,
        "total_charges": 411
      },
      {
        "pat_enc_csn_id": "0000540-008",
        "contact_date": "2024-12-06",
        "encounter_type": "Office Visit",
        "department_name": "Pulmonology",
        "provider_name": "Dr. Aisha Anderson",
        "chief_complaint": "Acute bronchitis, unspecified",
        "diagnosis_count": 3,
        "total_charges": 303
      }
    ]
  },
  "diagnoses": {
    "pat_id": "PAT0100540",
    "diagnoses": [
      {
        "dx_id": "0000540-dx-000",
        "pat_enc_csn_id": "0000540-000",
        "icd10_code": "F41.9",
        "diagnosis_name": "Anxiety disorder, unspecified",
        "chronic": true,
        "first_recorded": "2016-05-13"
      },
      {
        "dx_id": "0000540-dx-001",
        "pat_enc_csn_id": "0000540-000",
        "icd10_code": "N18.3",
        "diagnosis_name": "Chronic kidney disease, stage 3",
        "chronic": true,
        "first_recorded": "2007-05-13"
      },
      {
        "dx_id": "0000540-acu-000",
        "pat_enc_csn_id": "0000540-000",
        "icd10_code": "R10.9",
        "diagnosis_name": "Unspecified abdominal pain",
        "chronic": false,
        "first_recorded": "2026-03-25"
      },
      {
        "dx_id": "0000540-acu-002",
        "pat_enc_csn_id": "0000540-002",
        "icd10_code": "S00.93",
        "diagnosis_name": "Contusion of head",
        "chronic": false,
        "first_recorded": "2025-12-06"
      }
    ]
  },
  "accounts": {
    "pat_id": "PAT0100540",
    "summary": {
      "total_charges": 2615,
      "total_payments": 2217,
      "outstanding_balance": 398,
      "account_count": 1
    },
    "accounts": [
      {
        "hsp_account_id": "HSP000054000",
        "account_type": "Professional",
        "status": "Closed",
        "total_charges": 2615,
        "total_payments": 2217,
        "current_balance": 398,
        "primary_payer": "Highmark BCBS",
        "opened_date": "2025-01-05",
        "closed_date": "2025-11-17"
      }
    ]
  },
  "comparables": {
    "pat_id": "PAT0100540",
    "comparables": [
      {
        "pat_id": "PAT0100004",
        "full_name": "Carol Smith",
        "age": 71,
        "sex": "F",
        "chronic_overlap_count": 1,
        "encounter_count": 13,
        "total_charges": 4192
      },
      {
        "pat_id": "PAT0100010",
        "full_name": "Reshma O'Brien",
        "age": 74,
        "sex": "F",
        "chronic_overlap_count": 1,
        "encounter_count": 13,
        "total_charges": 12864
      },
      {
        "pat_id": "PAT0100046",
        "full_name": "Kimberly Okonkwo",
        "age": 70,
        "sex": "F",
        "chronic_overlap_count": 1,
        "encounter_count": 12,
        "total_charges": 43245
      },
      {
        "pat_id": "PAT0100120",
        "full_name": "Andrew Lopez",
        "age": 77,
        "sex": "M",
        "chronic_overlap_count": 1,
        "encounter_count": 6,
        "total_charges": 1601
      },
      {
        "pat_id": "PAT0100128",
        "full_name": "Mark Park",
        "age": 77,
        "sex": "M",
        "chronic_overlap_count": 1,
        "encounter_count": 6,
        "total_charges": 1775
      },
      {
        "pat_id": "PAT0100142",
        "full_name": "Maria Smith",
        "age": 73,
        "sex": "F",
        "chronic_overlap_count": 1,
        "encounter_count": 15,
        "total_charges": 52907
      }
    ]
  }
}