{
  "patient": {
    "pat_id": "PAT0100510",
    "med_rec_num": "MRN0200510",
    "full_name": "Carlos Kim",
    "birth_date": "1989-03-12",
    "age": 37,
    "sex": "M",
    "city": "Cranberry Twp",
    "zip_code": "16066",
    "primary_care_provider": "Dr. David Johnson",
    "active_chronic_count": 1,
    "encounter_count": 2,
    "total_charges": 411,
    "latitude": 40.68275,
    "longitude": -80.10269,
    "last_encounter_date": "2025-07-22",
    "race": "Hispanic/Latino",
    "ethnicity": "Not Hispanic or Latino",
    "mailing_address": "8711 Penn Rd",
    "state": "PA",
    "phone": "(412) 808-6055",
    "primary_care_department": "Family Medicine \u2014 North Hills"
  },
  "encounters": {
    "pat_id": "PAT0100510",
    "encounters": [
      {
        "pat_enc_csn_id": "0000510-000",
        "contact_date": "2025-07-22",
        "encounter_type": "Telehealth",
        "department_name": "Orthopedics",
        "provider_name": "Dr. David Johnson",
        "chief_complaint": null,
        "diagnosis_count": 1,
        "total_charges": 120
      },
      {
        "pat_enc_csn_id": "0000510-001",
        "contact_date": "2024-10-13",
        "encounter_type": "Office Visit",
        "department_name": "Family Medicine \u2014 North Hills",
        "provider_name": "Dr. Kenji Walsh",
        "chief_complaint": null,
        "diagnosis_count": 1,
        "total_charges": 291
      }
    ]
  },
  "diagnoses": {
    "pat_id": "PAT0100510",
    "diagnoses": [
      {
        "dx_id": "0000510-dx-000",
        "pat_enc_csn_id": "0000510-000",
        "icd10_code": "M54.50",
        "diagnosis_name": "Low back pain, unspecified",
        "chronic": true,
        "first_recorded": "2017-05-13"
      }
    ]
  },
  "accounts": {
    "pat_id": "PAT0100510",
    "summary": {
      "total_charges": 411,
      "total_payments": 382,
      "outstanding_balance": 29,
      "account_count": 1
    },
    "accounts": [
      {
        "hsp_account_id": "HSP000051000",
        "account_type": "Professional",
        "status": "Closed",
        "total_charges": 411,
        "total_payments": 382,
        "current_balance": 29,
        "primary_payer": "Medicaid",
        "opened_date": "2024-09-10",
        "closed_date": "2026-04-23"
      }
    ]
  },
  "comparables": {
    "pat_id": "PAT0100510",
    "comparables": [
      {
        "pat_id": "PAT0100007",
        "full_name": "David Okonkwo",
        "age": 37,
        "sex": "M",
        "chronic_overlap_count": 0,
        "encounter_count": 12,
        "total_charges": 2937
      },
      {
        "pat_id": "PAT0100012",
        "full_name": "Anil Singh",
        "age": 34,
        "sex": "M",
        "chronic_overlap_count": 0,
        "encounter_count": 11,
        "total_charges": 14790
      },
      {
        "pat_id": "PAT0100062",
        "full_name": "Christopher Okonkwo",
        "age": 38,
        "sex": "M",
        "chronic_overlap_count": 0,
        "encounter_count": 5,
        "total_charges": 6545
      },
      {
        "pat_id": "PAT0100117",
        "full_name": "Elizabeth Kim",
        "age": 31,
        "sex": "F",
        "chronic_overlap_count": 0,
        "encounter_count": 10,
        "total_charges": 33077
      },
      {
        "pat_id": "PAT0100123",
        "full_name": "Kevin Garcia",
        "age": 36,
        "sex": "M",
        "chronic_overlap_count": 0,
        "encounter_count": 1,
        "total_charges": 398
      },
      {
        "pat_id": "PAT0100158",
        "full_name": "Mark Gonzalez",
        "age": 35,
        "sex": "M",
        "chronic_overlap_count": 0,
        "encounter_count": 5,
        "total_charges": 22408
      }
    ]
  }
}