{
  "patient": {
    "pat_id": "PAT0101305",
    "med_rec_num": "MRN0201305",
    "full_name": "Paul Martin",
    "birth_date": "1970-10-16",
    "age": 56,
    "sex": "M",
    "city": "Cranberry Twp",
    "zip_code": "16066",
    "primary_care_provider": "Dr. Aisha Wilson",
    "active_chronic_count": 1,
    "encounter_count": 11,
    "total_charges": 16609,
    "latitude": 40.69001,
    "longitude": -80.10562,
    "last_encounter_date": "2026-05-11",
    "race": "White",
    "ethnicity": "Hispanic or Latino",
    "mailing_address": "492 Centre St",
    "state": "PA",
    "phone": "(412) 426-4065",
    "primary_care_department": "Pulmonology"
  },
  "encounters": {
    "pat_id": "PAT0101305",
    "encounters": [
      {
        "pat_enc_csn_id": "0001305-000",
        "contact_date": "2026-05-11",
        "encounter_type": "Office Visit",
        "department_name": "Internal Medicine \u2014 Squirrel Hill",
        "provider_name": "Dr. Aisha Wilson",
        "chief_complaint": null,
        "diagnosis_count": 1,
        "total_charges": 234
      },
      {
        "pat_enc_csn_id": "0001305-001",
        "contact_date": "2025-12-30",
        "encounter_type": "Telehealth",
        "department_name": "Pulmonology",
        "provider_name": "Dr. Aisha Wilson",
        "chief_complaint": null,
        "diagnosis_count": 1,
        "total_charges": 156
      },
      {
        "pat_enc_csn_id": "0001305-002",
        "contact_date": "2025-07-16",
        "encounter_type": "Emergency Visit",
        "department_name": "Urgent Care \u2014 Mt Lebanon",
        "provider_name": "Dr. Aisha Wilson",
        "chief_complaint": null,
        "diagnosis_count": 1,
        "total_charges": 6480
      },
      {
        "pat_enc_csn_id": "0001305-003",
        "contact_date": "2025-06-28",
        "encounter_type": "Office Visit",
        "department_name": "Endocrinology",
        "provider_name": "Dr. Michael Wong",
        "chief_complaint": "Urinary tract infection",
        "diagnosis_count": 2,
        "total_charges": 207
      },
      {
        "pat_enc_csn_id": "0001305-004",
        "contact_date": "2025-03-05",
        "encounter_type": "Office Visit",
        "department_name": "Endocrinology",
        "provider_name": "Dr. Sarah Hernandez",
        "chief_complaint": null,
        "diagnosis_count": 1,
        "total_charges": 378
      },
      {
        "pat_enc_csn_id": "0001305-005",
        "contact_date": "2024-12-21",
        "encounter_type": "Procedure",
        "department_name": "Psychiatry & Behavioral Health",
        "provider_name": "Dr. Maria Okonkwo",
        "chief_complaint": "Acute bronchitis, unspecified",
        "diagnosis_count": 2,
        "total_charges": 7016
      },
      {
        "pat_enc_csn_id": "0001305-006",
        "contact_date": "2024-12-15",
        "encounter_type": "Office Visit",
        "department_name": "OB-GYN",
        "provider_name": "Dr. Aisha Wilson",
        "chief_complaint": "Chest pain, unspecified",
        "diagnosis_count": 2,
        "total_charges": 407
      },
      {
        "pat_enc_csn_id": "0001305-007",
        "contact_date": "2024-08-24",
        "encounter_type": "Office Visit",
        "department_name": "OB-GYN",
        "provider_name": "Dr. Aisha Wilson",
        "chief_complaint": "Acute upper respiratory infection",
        "diagnosis_count": 2,
        "total_charges": 290
      },
      {
        "pat_enc_csn_id": "0001305-008",
        "contact_date": "2024-07-16",
        "encounter_type": "Telehealth",
        "department_name": "Psychiatry & Behavioral Health",
        "provider_name": "Dr. Aisha Wilson",
        "chief_complaint": "Acute bronchitis, unspecified",
        "diagnosis_count": 2,
        "total_charges": 208
      },
      {
        "pat_enc_csn_id": "0001305-009",
        "contact_date": "2024-06-12",
        "encounter_type": "Telehealth",
        "department_name": "Nephrology",
        "provider_name": "Dr. Sarah Hernandez",
        "chief_complaint": "Acute bronchitis, unspecified",
        "diagnosis_count": 2,
        "total_charges": 196
      },
      {
        "pat_enc_csn_id": "0001305-010",
        "contact_date": "2024-05-15",
        "encounter_type": "Procedure",
        "department_name": "Urgent Care \u2014 Mt Lebanon",
        "provider_name": "Dr. Aisha Wilson",
        "chief_complaint": "Unspecified abdominal pain",
        "diagnosis_count": 2,
        "total_charges": 1037
      }
    ]
  },
  "diagnoses": {
    "pat_id": "PAT0101305",
    "diagnoses": [
      {
        "dx_id": "0001305-dx-000",
        "pat_enc_csn_id": "0001305-000",
        "icd10_code": "E78.5",
        "diagnosis_name": "Hyperlipidemia, unspecified",
        "chronic": true,
        "first_recorded": "2017-05-13"
      }
    ]
  },
  "accounts": {
    "pat_id": "PAT0101305",
    "summary": {
      "total_charges": 16609,
      "total_payments": 11902,
      "outstanding_balance": 4707,
      "account_count": 3
    },
    "accounts": [
      {
        "hsp_account_id": "HSP000130500",
        "account_type": "Professional",
        "status": "Closed",
        "total_charges": 1395,
        "total_payments": 1157,
        "current_balance": 238,
        "primary_payer": "Aetna",
        "opened_date": "2026-01-29",
        "closed_date": "2026-03-05"
      },
      {
        "hsp_account_id": "HSP000130501",
        "account_type": "Hospital",
        "status": "Closed",
        "total_charges": 12123,
        "total_payments": 8818,
        "current_balance": 3305,
        "primary_payer": "Self-pay",
        "opened_date": "2025-01-27",
        "closed_date": "2025-12-04"
      },
      {
        "hsp_account_id": "HSP000130502",
        "account_type": "Imaging",
        "status": "Closed",
        "total_charges": 3091,
        "total_payments": 1927,
        "current_balance": 1164,
        "primary_payer": "Aetna",
        "opened_date": "2025-05-19",
        "closed_date": "2026-01-13"
      }
    ]
  },
  "comparables": {
    "pat_id": "PAT0101305",
    "comparables": [
      {
        "pat_id": "PAT0100018",
        "full_name": "Richard Gonzalez",
        "age": 50,
        "sex": "M",
        "chronic_overlap_count": 0,
        "encounter_count": 5,
        "total_charges": 981
      },
      {
        "pat_id": "PAT0100040",
        "full_name": "John Moore",
        "age": 50,
        "sex": "M",
        "chronic_overlap_count": 0,
        "encounter_count": 7,
        "total_charges": 2082
      },
      {
        "pat_id": "PAT0100195",
        "full_name": "Donna Chen",
        "age": 53,
        "sex": "F",
        "chronic_overlap_count": 0,
        "encounter_count": 4,
        "total_charges": 19298
      },
      {
        "pat_id": "PAT0100325",
        "full_name": "Michael Smith",
        "age": 52,
        "sex": "M",
        "chronic_overlap_count": 0,
        "encounter_count": 12,
        "total_charges": 3567
      },
      {
        "pat_id": "PAT0100353",
        "full_name": "James Williams",
        "age": 55,
        "sex": "M",
        "chronic_overlap_count": 0,
        "encounter_count": 12,
        "total_charges": 7886
      },
      {
        "pat_id": "PAT0100391",
        "full_name": "Joseph Kim",
        "age": 59,
        "sex": "M",
        "chronic_overlap_count": 0,
        "encounter_count": 3,
        "total_charges": 2053
      }
    ]
  }
}